{
  "_class": "symbolMaster",
  "allowsOverrides": true,
  "backgroundColor": {
    "_class": "color",
    "alpha": 1,
    "blue": 0.0784313725490196,
    "green": 0.09019607843137253,
    "red": 0.09803921568627451
  },
  "booleanOperation": 0,
  "changeIdentifier": 836,
  "clippingMaskMode": 0,
  "do_objectID": "483A608F-3D89-446F-BA19-55DC1677B26A",
  "exportOptions": {
    "_class": "exportOptions",
    "exportFormats": [
    ],
    "includedLayerIds": [
    ],
    "layerOptions": 0,
    "shouldTrim": false
  },
  "frame": {
    "_class": "rect",
    "constrainProportions": false,
    "height": 57,
    "width": 544,
    "x": 1310,
    "y": 704
  },
  "groupLayout": {
    "_class": "MSImmutableFreeformGroupLayout"
  },
  "hasBackgroundColor": false,
  "hasClickThrough": true,
  "hasClippingMask": false,
  "horizontalRulerData": {
    "_class": "rulerData",
    "base": 0,
    "guides": [
    ]
  },
  "includeBackgroundColorInExport": false,
  "includeBackgroundColorInInstance": false,
  "includeInCloudUpload": true,
  "isFixedToViewport": false,
  "isFlippedHorizontal": false,
  "isFlippedVertical": false,
  "isFlowHome": false,
  "isLocked": false,
  "isVisible": true,
  "layerListExpandedType": 2,
  "layers": [
    {
      "class": "text",
      "id": "89446410-D9C8-4D33-A8F5-84F032CE5365"
    },
    {
      "class": "group",
      "id": "A60F0A2E-3F78-4BA1-96C1-FF0458EA408C"
    },
    {
      "class": "text",
      "id": "2FBA44BB-E52E-4A79-B9E5-E4ED4EFD1A56"
    },
    {
      "class": "text",
      "id": "59625E30-C778-42DA-AE1A-9366AEBDBB21"
    },
    {
      "class": "group",
      "id": "25EB39A8-6C13-46E6-BCE0-61695CB565CB"
    }
  ],
  "name": "uiForms/input/filled and error'd/white bg/desktop",
  "nameIsFixed": true,
  "overrideProperties": [
    {
      "_class": "MSImmutableOverrideProperty",
      "canOverride": true,
      "overrideName": "59625E30-C778-42DA-AE1A-9366AEBDBB21_stringValue"
    },
    {
      "_class": "MSImmutableOverrideProperty",
      "canOverride": true,
      "overrideName": "89446410-D9C8-4D33-A8F5-84F032CE5365_stringValue"
    },
    {
      "_class": "MSImmutableOverrideProperty",
      "canOverride": true,
      "overrideName": "2FBA44BB-E52E-4A79-B9E5-E4ED4EFD1A56_stringValue"
    },
    {
      "_class": "MSImmutableOverrideProperty",
      "canOverride": true,
      "overrideName": "2FBA44BB-E52E-4A79-B9E5-E4ED4EFD1A56_textStyle"
    }
  ],
  "presetDictionary": {
  },
  "resizesContent": true,
  "resizingConstraint": 63,
  "resizingType": 0,
  "rotation": 0,
  "shouldBreakMaskChain": true,
  "style": {
    "_class": "style",
    "blur": {
      "_class": "blur",
      "center": "{0.5, 0.5}",
      "isEnabled": false,
      "motionAngle": 0,
      "radius": 10,
      "saturation": 1,
      "type": 0
    },
    "borderOptions": {
      "_class": "borderOptions",
      "dashPattern": [
      ],
      "isEnabled": true,
      "lineCapStyle": 0,
      "lineJoinStyle": 0
    },
    "borders": [
    ],
    "colorControls": {
      "_class": "colorControls",
      "brightness": 0,
      "contrast": 1,
      "hue": 0,
      "isEnabled": true,
      "saturation": 1
    },
    "contextSettings": {
      "_class": "graphicsContextSettings",
      "blendMode": 0,
      "opacity": 1
    },
    "do_objectID": "E8E369EB-1104-4A74-ADF7-68D0741E76C3",
    "endMarkerType": 0,
    "fills": [
    ],
    "innerShadows": [
    ],
    "miterLimit": 10,
    "shadows": [
    ],
    "startMarkerType": 0,
    "windingRule": 1
  },
  "symbolID": "89DAB9FB-FEE2-4F56-B00F-63230C8DA39F",
  "verticalRulerData": {
    "_class": "rulerData",
    "base": 0,
    "guides": [
    ]
  }
}