{
  "_class": "shapePath",
  "booleanOperation": -1,
  "clippingMaskMode": 0,
  "do_objectID": "FC289DE3-8097-4FD6-82DE-CACC1E990B8E",
  "edited": true,
  "exportOptions": {
    "_class": "exportOptions",
    "exportFormats": [
    ],
    "includedLayerIds": [
    ],
    "layerOptions": 0,
    "shouldTrim": false
  },
  "frame": {
    "_class": "rect",
    "constrainProportions": false,
    "height": 164.8440000000001,
    "width": 131.328,
    "x": 626.8860000000001,
    "y": 78.65999999999985
  },
  "hasClippingMask": false,
  "isClosed": true,
  "isFixedToViewport": false,
  "isFlippedHorizontal": false,
  "isFlippedVertical": false,
  "isLocked": false,
  "isVisible": true,
  "layerListExpandedType": 0,
  "name": "Path",
  "nameIsFixed": false,
  "pointRadiusBehaviour": 1,
  "points": [
    {
      "_class": "curvePoint",
      "cornerRadius": 0,
      "curveFrom": "{0.85156249999999978, 1}",
      "curveMode": 3,
      "curveTo": "{0.26302083333333276, 1}",
      "hasCurveFrom": true,
      "hasCurveTo": true,
      "point": "{0.52604166666666641, 1}"
    },
    {
      "_class": "curvePoint",
      "cornerRadius": 0,
      "curveFrom": "{1, 0.57468879668049455}",
      "curveMode": 3,
      "curveTo": "{1, 0.83817427385891885}",
      "hasCurveFrom": true,
      "hasCurveTo": true,
      "point": "{1, 0.69917012448132698}"
    },
    {
      "_class": "curvePoint",
      "cornerRadius": 0,
      "curveFrom": "{0.671875, 0.40456431535269455}",
      "curveMode": 4,
      "curveTo": "{0.91666666666666696, 0.46887966804978914}",
      "hasCurveFrom": false,
      "hasCurveTo": true,
      "point": "{0.671875, 0.40456431535269455}"
    },
    {
      "_class": "curvePoint",
      "cornerRadius": 0,
      "curveFrom": "{0.41145833333333298, 0.33817427385892163}",
      "curveMode": 4,
      "curveTo": "{0.47395833333333276, 0.35477178423236488}",
      "hasCurveFrom": true,
      "hasCurveTo": false,
      "point": "{0.47395833333333276, 0.35477178423236488}"
    },
    {
      "_class": "curvePoint",
      "cornerRadius": 0,
      "curveFrom": "{0.38541666666666663, 0.25311203319502162}",
      "curveMode": 2,
      "curveTo": "{0.38541666666666663, 0.31535269709543234}",
      "hasCurveFrom": true,
      "hasCurveTo": true,
      "point": "{0.38541666666666663, 0.28215767634854588}"
    },
    {
      "_class": "curvePoint",
      "cornerRadius": 0,
      "curveFrom": "{0.58333333333333304, 0.21784232365145134}",
      "curveMode": 3,
      "curveTo": "{0.41666666666666607, 0.21784232365145134}",
      "hasCurveFrom": true,
      "hasCurveTo": true,
      "point": "{0.50520833333333315, 0.21784232365145134}"
    },
    {
      "_class": "curvePoint",
      "cornerRadius": 0,
      "curveFrom": "{0.79947916666666619, 0.31535269709543234}",
      "curveMode": 4,
      "curveTo": "{0.70312499999999956, 0.24066390041493507}",
      "hasCurveFrom": false,
      "hasCurveTo": true,
      "point": "{0.79947916666666619, 0.31535269709543234}"
    },
    {
      "_class": "curvePoint",
      "cornerRadius": 0,
      "curveFrom": "{0.85156249999999978, 0.037344398340248643}",
      "curveMode": 4,
      "curveTo": "{0.99218749999999944, 0.14107883817427019}",
      "hasCurveFrom": true,
      "hasCurveTo": false,
      "point": "{0.99218749999999944, 0.14107883817427019}"
    },
    {
      "_class": "curvePoint",
      "cornerRadius": 0,
      "curveFrom": "{0.22395833333333279, 0}",
      "curveMode": 3,
      "curveTo": "{0.66666666666666607, 0}",
      "hasCurveFrom": true,
      "hasCurveTo": true,
      "point": "{0.51041666666666619, 0}"
    },
    {
      "_class": "curvePoint",
      "cornerRadius": 0,
      "curveFrom": "{0.046874999999999618, 0.41908713692945943}",
      "curveMode": 3,
      "curveTo": "{0.046874999999999618, 0.13900414937759187}",
      "hasCurveFrom": true,
      "hasCurveTo": true,
      "point": "{0.046874999999999618, 0.29460580912862694}"
    },
    {
      "_class": "curvePoint",
      "cornerRadius": 0,
      "curveFrom": "{0.32291666666666596, 0.57261410788381617}",
      "curveMode": 4,
      "curveTo": "{0.13020833333333268, 0.52282157676348651}",
      "hasCurveFrom": false,
      "hasCurveTo": true,
      "point": "{0.32291666666666596, 0.57261410788381617}"
    },
    {
      "_class": "curvePoint",
      "cornerRadius": 0,
      "curveFrom": "{0.62239583333333304, 0.64315352697095129}",
      "curveMode": 4,
      "curveTo": "{0.52604166666666641, 0.62033195020746756}",
      "hasCurveFrom": true,
      "hasCurveTo": false,
      "point": "{0.52604166666666641, 0.62033195020746756}"
    },
    {
      "_class": "curvePoint",
      "cornerRadius": 0,
      "curveFrom": "{0.66145833333333304, 0.74896265560165665}",
      "curveMode": 3,
      "curveTo": "{0.66145833333333304, 0.66390041493775676}",
      "hasCurveFrom": true,
      "hasCurveTo": true,
      "point": "{0.66145833333333304, 0.71161825726140804}"
    },
    {
      "_class": "curvePoint",
      "cornerRadius": 0,
      "curveFrom": "{0.41927083333333265, 0.78215767634854871}",
      "curveMode": 3,
      "curveTo": "{0.61197916666666685, 0.78215767634854871}",
      "hasCurveFrom": true,
      "hasCurveTo": true,
      "point": "{0.53124999999999944, 0.78215767634854871}"
    },
    {
      "_class": "curvePoint",
      "cornerRadius": 0,
      "curveFrom": "{0.17968749999999969, 0.66390041493775676}",
      "curveMode": 4,
      "curveTo": "{0.26562500000000017, 0.7282157676348513}",
      "hasCurveFrom": false,
      "hasCurveTo": true,
      "point": "{0.17968749999999969, 0.66390041493775676}"
    },
    {
      "_class": "curvePoint",
      "cornerRadius": 0,
      "curveFrom": "{0.098958333333333204, 0.91908713692945665}",
      "curveMode": 4,
      "curveTo": "{0, 0.85062240663899991}",
      "hasCurveFrom": true,
      "hasCurveTo": false,
      "point": "{0, 0.85062240663899991}"
    }
  ],
  "resizingConstraint": 63,
  "resizingType": 0,
  "rotation": 0,
  "shouldBreakMaskChain": false,
  "style": {
    "_class": "style",
    "blur": {
      "_class": "blur",
      "center": "{0.5, 0.5}",
      "isEnabled": false,
      "motionAngle": 0,
      "radius": 10,
      "saturation": 1,
      "type": 0
    },
    "borderOptions": {
      "_class": "borderOptions",
      "dashPattern": [
      ],
      "isEnabled": true,
      "lineCapStyle": 0,
      "lineJoinStyle": 0
    },
    "borders": [
      {
        "_class": "border",
        "color": {
          "_class": "color",
          "alpha": 1,
          "blue": 0.7294117647058823,
          "green": 0.7333333333333333,
          "red": 0.7333333333333333
        },
        "contextSettings": {
          "_class": "graphicsContextSettings",
          "blendMode": 0,
          "opacity": 1
        },
        "fillType": 0,
        "gradient": {
          "_class": "gradient",
          "elipseLength": 0,
          "from": "{0.5, 0}",
          "gradientType": 0,
          "stops": [
            {
              "_class": "gradientStop",
              "color": {
                "_class": "color",
                "alpha": 1,
                "blue": 1,
                "green": 1,
                "red": 1
              },
              "position": 0
            },
            {
              "_class": "gradientStop",
              "color": {
                "_class": "color",
                "alpha": 1,
                "blue": 0,
                "green": 0,
                "red": 0
              },
              "position": 1
            }
          ],
          "to": "{0.5, 1}"
        },
        "isEnabled": true,
        "position": 0,
        "thickness": 1
      }
    ],
    "colorControls": {
      "_class": "colorControls",
      "brightness": 0,
      "contrast": 1,
      "hue": 0,
      "isEnabled": false,
      "saturation": 1
    },
    "contextSettings": {
      "_class": "graphicsContextSettings",
      "blendMode": 0,
      "opacity": 1
    },
    "do_objectID": "6D8FD6BB-BE3E-4CAD-83AA-21C9C7C9395D",
    "endMarkerType": 0,
    "fills": [
      {
        "_class": "fill",
        "color": {
          "_class": "color",
          "alpha": 1,
          "blue": 0.0784313725490196,
          "green": 0.09019607843137253,
          "red": 0.09803921568627451
        },
        "contextSettings": {
          "_class": "graphicsContextSettings",
          "blendMode": 0,
          "opacity": 1
        },
        "fillType": 0,
        "gradient": {
          "_class": "gradient",
          "elipseLength": 0,
          "from": "{0.5, 0}",
          "gradientType": 0,
          "stops": [
            {
              "_class": "gradientStop",
              "color": {
                "_class": "color",
                "alpha": 1,
                "blue": 1,
                "green": 1,
                "red": 1
              },
              "position": 0
            },
            {
              "_class": "gradientStop",
              "color": {
                "_class": "color",
                "alpha": 1,
                "blue": 0,
                "green": 0,
                "red": 0
              },
              "position": 1
            }
          ],
          "to": "{0.5, 1}"
        },
        "isEnabled": false,
        "noiseIndex": 0,
        "noiseIntensity": 0,
        "patternFillType": 1,
        "patternTileScale": 1
      }
    ],
    "innerShadows": [
    ],
    "miterLimit": 10,
    "shadows": [
    ],
    "startMarkerType": 0,
    "windingRule": 0
  }
}